clearapi/__init__.py
clearapi/colors.py
apiclear-0.1.dist-info/METADATA
apiclear-0.1.dist-info/WHEEL
apiclear-0.1.dist-info/top_level.txt
apiclear-0.1.dist-info/RECORD
