Metadata-Version: 2.1
Name: apiclear
Version: 0.1
Summary: Uma package para ajudar nas cores.
Author: franciandev22
Author-email: h4xxx99@gmail.com
